Workbook

Sheet H_PSA
A1: FOL_PROG | B1: CVE_EDO | C1: ESTADO | D1: MUNICIPIO | E1: SOLICITANT | F1: TIPO_PROP | G1: CONCEPTO | H1: ESQUEMA | I1: SUP_HA | J1: MONTO_CNF | K1: MONTO_PI | L1: MONTO_TOT | M1: EJERCICIO | N1: GERENCIA
A2: PSAAAP5525160002 | B2: 16 | C2: MICHOACÁN DE OCAMPO | D2: SALVADOR ESCALANTE | E2: COMUNIDA INDIGENA VILLA ESCALANTE | F2: COMUNIDAD | G2: SA.1 PAGO POR SERVICIOS AMBIENTALES | H2: PSA NACIONAL | I2: 1000 | J2: 2607000 | K2: 0 | L2: =+IF(K2=0,J2,J2+K2) -> 2607000 | M2: 2025 | N2: SERVICIOS AMBIENTALES Y CONSERVACIÓN DE LA BIODIVERSIDAD
A3: PSAAAP5525160069 | B3: 16 | C3: MICHOACÁN DE OCAMPO | D3: NAHUATZEN | E3: COMUNIDAD INDIGENA DE SEVINA | F3: COMUNIDAD | G3: SA.1 PAGO POR SERVICIOS AMBIENTALES | H3: PSA NACIONAL | I3: 508 | J3: 1009783 | K3: 0 | L3: =+IF(K3=0,J3,J3+K3) -> 1009783 | M3: 2025 | N3: SERVICIOS AMBIENTALES Y CONSERVACIÓN DE LA BIODIVERSIDAD
A4: PSAAAP4924010001 | B4: 01 | C4: AGUASCALIENTES | D4: JESÚS MARÍA | E4: EDUARDO RODRIGUEZ MARTINEZ | F4: PEQUEÑO PROPIETARIO | G4: SA.1 PAGO POR SERVICIOS AMBIENTALES | H4: PSA NACIONAL | I4: 107.84 | J4: 236775 | K4: 0 | L4: =+IF(K4=0,J4,J4+K4) -> 236775 | M4: 2024 | N4: SERVICIOS AMBIENTALES Y CONSERVACIÓN DE LA BIODIVERSIDAD
A5: PSAAAP4924010004 | B5: 01 | C5: AGUASCALIENTES | D5: SAN JOSÉ DE GRACIA | E5: JOSE CARLOS LOZANO RIVERA RIO | F5: PEQUEÑO PROPIETARIO | G5: SA.1 PAGO POR SERVICIOS AMBIENTALES | H5: PSA NACIONAL | I5: 100 | J5: 241880 | K5: 0 | L5: =+IF(K5=0,J5,J5+K5) -> 241880 | M5: 2024 | N5: SERVICIOS AMBIENTALES Y CONSERVACIÓN DE LA BIODIVERSIDAD
A6: PSAAAP4924140049 | B6: 14 | C6: JALISCO | D6: TLAJOMULCO DE ZÚÑIGA | E6: COMUNIDAD INDIGENA DE TLAJOMULCO DE ZUÑIGA | F6: COMUNIDAD | G6: SA.1 PAGO POR SERVICIOS AMBIENTALES | H6: PSA NACIONAL | I6: 614.61 | J6: 1026202 | K6: 0 | L6: =+IF(K6=0,J6,J6+K6) -> 1026202 | M6: 2024 | N6: SERVICIOS AMBIENTALES Y CONSERVACIÓN DE LA BIODIVERSIDAD
A7: PSAAAP4924180008 | B7: 18 | C7: NAYARIT | D7: DEL NAYAR | E7: COMUNIDAD INDIGENA POTRERO DE LA PALMITA | F7: COMUNIDAD | G7: SA.1 PAGO POR SERVICIOS AMBIENTALES | H7: PSA NACIONAL | I7: 1893.44 | J7: 3366582 | K7: 0 | L7: =+IF(K7=0,J7,J7+K7) -> 3366582 | M7: 2024 | N7: SERVICIOS AMBIENTALES Y CONSERVACIÓN DE LA BIODIVERSIDAD
A8: PSAAAP4924180021 | B8: 18 | C8: NAYARIT | D8: DEL NAYAR | E8: EJIDO AGUAMILPA | F8: EJIDO | G8: SA.1 PAGO POR SERVICIOS AMBIENTALES | H8: PSA NACIONAL | I8: 1974.46 | J8: 3503149 | K8: 0 | L8: =+IF(K8=0,J8,J8+K8) -> 3503149 | M8: 2024 | N8: SERVICIOS AMBIENTALES Y CONSERVACIÓN DE LA BIODIVERSIDAD
A9: PSAAAP4924320007 | B9: 32 | C9: ZACATECAS | D9: SUSTICACÁN | E9: COMUNIDAD EL CHIQUIHUITE | F9: COMUNIDAD | G9: SA.1 PAGO POR SERVICIOS AMBIENTALES | H9: PSA NACIONAL | I9: 1699.48 | J9: 2918300 | K9: 0 | L9: =+IF(K9=0,J9,J9+K9) -> 2918300 | M9: 2024 | N9: SERVICIOS AMBIENTALES Y CONSERVACIÓN DE LA BIODIVERSIDAD
A10: PSAAAP4924160017 | B10: 16 | C10: MICHOACÁN DE OCAMPO | D10: LOS REYES | E10: COMUNIDAD INDIGENA DE PAMATACUARO | F10: COMUNIDAD | G10: SA.1 PAGO POR SERVICIOS AMBIENTALES | H10: PSA NACIONAL | I10: 1915.92 | J10: 3746466 | K10: 0 | L10: =+IF(K10=0,J10,J10+K10) -> 3746466 | M10: 2024 | N10: SERVICIOS AMBIENTALES Y CONSERVACIÓN DE LA BIODIVERSIDAD
A11: PSAAAP4924160004 | B11: 16 | C11: MICHOACÁN DE OCAMPO | D11: PARACHO | E11: COMUNIDAD INDIGENA CHERAN ATZICURIN | F11: COMUNIDAD | G11: SA.1 PAGO POR SERVICIOS AMBIENTALES | H11: PSA NACIONAL | I11: 420.69 | J11: 821652 | K11: 0 | L11: =+IF(K11=0,J11,J11+K11) -> 821652 | M11: 2024 | N11: SERVICIOS AMBIENTALES Y CONSERVACIÓN DE LA BIODIVERSIDAD
A12: PSAAAP4924160032 | B12: 16 | C12: MICHOACÁN DE OCAMPO | D12: TANGANCÍCUARO | E12: EJIDO TENHUECHO SEGUNDO | F12: EJIDO | G12: SA.1 PAGO POR SERVICIOS AMBIENTALES | H12: PSA NACIONAL | I12: 783.98 | J12: 1598412 | K12: 0 | L12: =+IF(K12=0,J12,J12+K12) -> 1598412 | M12: 2024 | N12: SERVICIOS AMBIENTALES Y CONSERVACIÓN DE LA BIODIVERSIDAD
A13: PSAAAP4924160016 | B13: 16 | C13: MICHOACÁN DE OCAMPO | D13: NAHUATZEN | E13: COMUNIDAD INDÍGENA COMACHUEN | F13: COMUNIDAD | G13: SA.1 PAGO POR SERVICIOS AMBIENTALES | H13: PSA NACIONAL | I13: 1185.55 | J13: 2827549 | K13: 0 | L13: =+IF(K13=0,J13,J13+K13) -> 2827549 | M13: 2024 | N13: SERVICIOS AMBIENTALES Y CONSERVACIÓN DE LA BIODIVERSIDAD
... A90: FPB1AP3522180004 | B90: 18 | C90: NAYARIT | D90: DEL NAYAR | E90: COMUNIDAD INDIGENA SANTA TERESA | F90: COMUNIDAD | G90: FONDO PATRIMONIAL DE BIODIVERSIDAD | H90: FPB | I90: 2500 | J90: 6450000 | K90: 0 | L90: =+IF(K90=0,J90,J90+K90) -> 6450000 | M90: 2022 | N90: SERVICIOS AMBIENTALES Y CONSERVACIÓN DE LA BIODIVERSIDAD
A91: PFCMAP5825160016 | B91: 16 | C91: =+VLOOKUP(B91,EDOS!$A$1:$B$33,2,0) -> MICHOACÁN DE OCAMPO | D91: IRIMBO | E91: YOLANDA HERNANDEZ MARIN | G91: PFC.3 MANTENIMIENTO DE PLANTACIONES FORESTALES COMERCIALES 2025 | I91: 1.43 | M91: 2025 | N91: PLANTACIONES FORESTALES COMERCIALES
A92: PFCMAP5825160014 | B92: 16 | C92: =+VLOOKUP(B92,EDOS!$A$1:$B$33,2,0) -> MICHOACÁN DE OCAMPO | D92: ZACAPU | E92: EJIDO TIRINDARO | G92: PFC.3 MANTENIMIENTO DE PLANTACIONES FORESTALES COMERCIALES 2025 | I92: 17.42 | M92: 2025 | N92: PLANTACIONES FORESTALES COMERCIALES
A93: PFCMAP5825160006 | B93: 16 | C93: =+VLOOKUP(B93,EDOS!$A$1:$B$33,2,0) -> MICHOACÁN DE OCAMPO | D93: TANGANCÍCUARO | E93: COMUNIDAD INDIGENA DE PATAMBAN | G93: PFC.3 MANTENIMIENTO DE PLANTACIONES FORESTALES COMERCIALES 2025 | I93: 35.88 | M93: 2025 | N93: PLANTACIONES FORESTALES COMERCIALES
A94: PFCMAP5825160013 | B94: 16 | C94: =+VLOOKUP(B94,EDOS!$A$1:$B$33,2,0) -> MICHOACÁN DE OCAMPO | D94: ZACAPU | E94: EJIDO BUENA VISTA | G94: PFC.3 MANTENIMIENTO DE PLANTACIONES FORESTALES COMERCIALES 2025 | I94: 50 | M94: 2025 | N94: PLANTACIONES FORESTALES COMERCIALES
A95: PFC1AP4724160007 | B95: 16 | C95: =+VLOOKUP(B95,EDOS!$A$1:$B$33,2,0) -> MICHOACÁN DE OCAMPO | D95: IRIMBO | E95: YOLANDA HERNANDEZ MARIN | G95: PFCA.1 PLANTACIONES FORESTALES COMERCIALES 2024 | I95: 1.9 | M95: 2024 | N95: PLANTACIONES FORESTALES COMERCIALES
A96: PFCMAP5825160010 | B96: 16 | C96: =+VLOOKUP(B96,EDOS!$A$1:$B$33,2,0) -> MICHOACÁN DE OCAMPO | D96: CHERÁN | E96: JOSUE VELAZQUEZ VELAZQUEZ | G96: PFC.3 MANTENIMIENTO DE PLANTACIONES FORESTALES COMERCIALES 2025 | I96: 50 | M96: 2025 | N96: PLANTACIONES FORESTALES COMERCIALES
A97: PFCMAP5825150011 | B97: 15 | C97: =+VLOOKUP(B97,EDOS!$A$1:$B$33,2,0) -> MÉXICO | D97: XONACATLÁN | E97: SALVADOR ROSAS SAAVEDRA | G97: PFC.3 MANTENIMIENTO DE PLANTACIONES FORESTALES COMERCIALES 2025 | I97: 1 | M97: 2025 | N97: PLANTACIONES FORESTALES COMERCIALES
A98: PFCMAP5825160009 | B98: 16 | C98: =+VLOOKUP(B98,EDOS!$A$1:$B$33,2,0) -> MICHOACÁN DE OCAMPO | D98: CHERÁN | E98: J. ROSALIO MACIAS GUARDIAN | G98: PFC.3 MANTENIMIENTO DE PLANTACIONES FORESTALES COMERCIALES 2025 | I98: 49.65 | M98: 2025 | N98: PLANTACIONES FORESTALES COMERCIALES
A99: PFCMAP5825160022 | B99: 16 | C99: =+VLOOKUP(B99,EDOS!$A$1:$B$33,2,0) -> MICHOACÁN DE OCAMPO | D99: CHERÁN | E99: JOSEFINA ESTRADA VELAZQUEZ | G99: PFC.3 MANTENIMIENTO DE PLANTACIONES FORESTALES COMERCIALES 2025 | I99: 27.85 | M99: 2025 | N99: PLANTACIONES FORESTALES COMERCIALES
A100: PFCMAP5825160030 | B100: 16 | C100: =+VLOOKUP(B100,EDOS!$A$1:$B$33,2,0) -> MICHOACÁN DE OCAMPO | D100: ZINAPÉCUARO | E100: EJIDO UCAREO | G100: PFC.3 MANTENIMIENTO DE PLANTACIONES FORESTALES COMERCIALES 2025 | I100: 35.33 | M100: 2025 | N100: PLANTACIONES FORESTALES COMERCIALES
A101: PFCMAP5825160024 | B101: 16 | C101: =+VLOOKUP(B101,EDOS!$A$1:$B$33,2,0) -> MICHOACÁN DE OCAMPO | D101: CHERÁN | E101: FRANCISCO NINIZ SILVA | G101: PFC.3 MANTENIMIENTO DE PLANTACIONES FORESTALES COMERCIALES 2025 | I101: 50 | M101: 2025 | N101: PLANTACIONES FORESTALES COMERCIALES
A102: PFCMAP5825160017 | B102: 16 | C102: =+VLOOKUP(B102,EDOS!$A$1:$B$33,2,0) -> MICHOACÁN DE OCAMPO | D102: IRIMBO | E102: MIRASOL SOTO CORREA | G102: PFC.3 MANTENIMIENTO DE PLANTACIONES FORESTALES COMERCIALES 2025 | I102: 13.95 | M102: 2025 | N102: PLANTACIONES FORESTALES COMERCIALES
... A104: PFCPAP5825160009 | B104: 16 | C104: =+VLOOKUP(B104,EDOS!$A$1:$B$33,2,0) -> MICHOACÁN DE OCAMPO | D104: ZACAPU | E104: EJIDO BUENA VISTA | G104: PFC.1 PLANTACIONES FORESTALES COMERCIALES 2025 | I104: 18.2 | M104: 2025 | N104: PLANTACIONES FORESTALES COMERCIALES
A105: ACOMAP5725160001 | B105: 16 | C105: MICHOACÁN DE OCAMPO | D105: QUERÉNDARO | E105: EJIDO OTZUMATLAN O RIO DE PARRAS | G105: MFC.2.7 ACOMPAÑAMIENTO A LAS AUDITORÍAS TÉCNICAS PREVENTIVAS (ATP), CERTIFICACIÓN FORESTAL NACIONAL O INTERNACIONAL O AUDITORIAS INTERMEDIAS 2025 | J105: 63283 | M105: 2025 | N105: MANEJO FORESTAL COMUNITARIO
A106: ACOMAP5725160003 | B106: 16 | C106: MICHOACÁN DE OCAMPO | D106: TLALPUJAHUA | E106: EJIDO PUERTO BERMEO | G106: MFC.2.7 ACOMPAÑAMIENTO A LAS AUDITORÍAS TÉCNICAS PREVENTIVAS (ATP), CERTIFICACIÓN FORESTAL NACIONAL O INTERNACIONAL O AUDITORIAS INTERMEDIAS 2025 | J106: 139960 | M106: 2025 | N106: MANEJO FORESTAL COMUNITARIO
A107: ACTPAP5725010002 | B107: 01 | C107: AGUASCALIENTES | D107: EL LLANO | E107: EJIDO PALO ALTO | G107: MFC.3.1 ACTUALIZACIÓN DEL PADRÓN DE EJIDATARIOS O COMUNEROS 2025 | J107: 70000 | M107: 2025 | N107: MANEJO FORESTAL COMUNITARIO
A108: ACTPAP5725100015 | B108: 10 | C108: DURANGO | D108: MEZQUITAL | E108: SAN FRANCISCO DE OCOTAN | G108: MFC.3.1 ACTUALIZACIÓN DEL PADRÓN DE EJIDATARIOS O COMUNEROS 2025 | J108: 70000 | M108: 2025 | N108: MANEJO FORESTAL COMUNITARIO
A109: APECAP4023100019 | B109: 10 | C109: DURANGO | D109: MEZQUITAL | E109: COMUNIDAD SAN ANTONIO DE PADUA | G109: MFCCV.2.2.1 ACTUALIZACIÓN DEL PADRÓN DE EJIDATARIOS O COMUNEROS | J109: 70000 | M109: 2023 | N109: MANEJO FORESTAL COMUNITARIO
A110: APECAP4624100007 | B110: 10 | C110: DURANGO | D110: MEZQUITAL | E110: COMUNIDAD SANTA MARIA DE OCOTAN Y XOCONOXTLE | G110: MFCCV.2.2.1 ACTUALIZACIÓN DEL PADRÓN DE EJIDATARIOS O COMUNEROS 2024 | J110: 70000 | M110: 2024 | N110: MANEJO FORESTAL COMUNITARIO
A111: APECAP4624100040 | B111: 10 | C111: DURANGO | D111: SÚCHIL | E111: EJIDO SAN ANTONIO DE MULEROS | G111: MFCCV.2.2.1 ACTUALIZACIÓN DEL PADRÓN DE EJIDATARIOS O COMUNEROS 2024 | J111: 70000 | M111: 2024 | N111: MANEJO FORESTAL COMUNITARIO
A112: APECAP4624100041 | B112: 10 | C112: DURANGO | D112: SÚCHIL | E112: EJIDO LOS AZULES | G112: MFCCV.2.2.1 ACTUALIZACIÓN DEL PADRÓN DE EJIDATARIOS O COMUNEROS 2024 | J112: 70000 | M112: 2024 | N112: MANEJO FORESTAL COMUNITARIO
A113: APECAP4624110002 | B113: 11 | C113: GUANAJUATO | D113: SAN MIGUEL DE ALLENDE | E113: EJIDO LA HUERTA | G113: MFCCV.2.2.1 ACTUALIZACIÓN DEL PADRÓN DE EJIDATARIOS O COMUNEROS 2024 | J113: 70000 | M113: 2024 | N113: MANEJO FORESTAL COMUNITARIO
A114: APECAP4624110009 | B114: 11 | C114: GUANAJUATO | D114: SAN MIGUEL DE ALLENDE | E114: EJIDO TIERRA BLANCA | G114: MFCCV.2.2.1 ACTUALIZACIÓN DEL PADRÓN DE EJIDATARIOS O COMUNEROS 2024 | J114: 70000 | M114: 2024 | N114: MANEJO FORESTAL COMUNITARIO
A115: APECAP4624150012 | B115: 15 | C115: MÉXICO | D115: TEMOAYA | E115: EJIDO SAN PEDRO ARRIBA | G115: MFCCV.2.2.1 ACTUALIZACIÓN DEL PADRÓN DE EJIDATARIOS O COMUNEROS 2024 | J115: 70000 | M115: 2024 | N115: MANEJO FORESTAL COMUNITARIO
A116: APECAP4624150017 | B116: 15 | C116: MÉXICO | D116: SAN JOSÉ DEL RINCÓN | E116: EJIDO SAN JUAN PALO SECO | G116: MFCCV.2.2.1 ACTUALIZACIÓN DEL PADRÓN DE EJIDATARIOS O COMUNEROS 2024 | J116: 70000 | M116: 2024 | N116: MANEJO FORESTAL COMUNITARIO
... A336: TURIAP4624220001 | B336: 22 | C336: QUERÉTARO | D336: AMEALCO DE BONFIL | E336: LAGUNA DE SERVIN | G336: MFCCV.2.1.8 TURISMO EN ÁREAS FORESTALES 2024 | J336: 229215 | M336: 2024 | N336: MANEJO FORESTAL COMUNITARIO

Sheet H_PFC
A1: FOL_PROG | B1: CVE_EDO | C1: ESTADO | D1: MUNICIPIO | E1: SOLICITANT | F1: TIPO_PROP | G1: CONCEPTO | H1: ESQUEMA | I1: SUP_HA | J1: MONTO_CNF | K1: MONTO_PI | L1: MONTO_TOT | M1: EJERCICIO | N1: GERENCIA
A2: PFCMAP5825160016 | B2: 16 | C2: =+VLOOKUP(B2,EDOS!$A$1:$B$33,2,0) -> MICHOACÁN DE OCAMPO | D2: IRIMBO | E2: YOLANDA HERNANDEZ MARIN | G2: PFC.3 MANTENIMIENTO DE PLANTACIONES FORESTALES COMERCIALES 2025 | I2: 1.43 | M2: 2025 | N2: PLANTACIONES FORESTALES COMERCIALES
A3: PFCMAP5825160014 | B3: 16 | C3: =+VLOOKUP(B3,EDOS!$A$1:$B$33,2,0) -> MICHOACÁN DE OCAMPO | D3: ZACAPU | E3: EJIDO TIRINDARO | G3: PFC.3 MANTENIMIENTO DE PLANTACIONES FORESTALES COMERCIALES 2025 | I3: 17.42 | M3: 2025 | N3: PLANTACIONES FORESTALES COMERCIALES
A4: PFCMAP5825160006 | B4: 16 | C4: =+VLOOKUP(B4,EDOS!$A$1:$B$33,2,0) -> MICHOACÁN DE OCAMPO | D4: TANGANCÍCUARO | E4: COMUNIDAD INDIGENA DE PATAMBAN | G4: PFC.3 MANTENIMIENTO DE PLANTACIONES FORESTALES COMERCIALES 2025 | I4: 35.88 | M4: 2025 | N4: PLANTACIONES FORESTALES COMERCIALES
A5: PFCMAP5825160013 | B5: 16 | C5: =+VLOOKUP(B5,EDOS!$A$1:$B$33,2,0) -> MICHOACÁN DE OCAMPO | D5: ZACAPU | E5: EJIDO BUENA VISTA | G5: PFC.3 MANTENIMIENTO DE PLANTACIONES FORESTALES COMERCIALES 2025 | I5: 50 | M5: 2025 | N5: PLANTACIONES FORESTALES COMERCIALES
A6: PFC1AP4724160007 | B6: 16 | C6: =+VLOOKUP(B6,EDOS!$A$1:$B$33,2,0) -> MICHOACÁN DE OCAMPO | D6: IRIMBO | E6: YOLANDA HERNANDEZ MARIN | G6: PFCA.1 PLANTACIONES FORESTALES COMERCIALES 2024 | I6: 1.9 | M6: 2024 | N6: PLANTACIONES FORESTALES COMERCIALES
A7: PFCMAP5825160010 | B7: 16 | C7: =+VLOOKUP(B7,EDOS!$A$1:$B$33,2,0) -> MICHOACÁN DE OCAMPO | D7: CHERÁN | E7: JOSUE VELAZQUEZ VELAZQUEZ | G7: PFC.3 MANTENIMIENTO DE PLANTACIONES FORESTALES COMERCIALES 2025 | I7: 50 | M7: 2025 | N7: PLANTACIONES FORESTALES COMERCIALES
A8: PFCMAP5825150011 | B8: 15 | C8: =+VLOOKUP(B8,EDOS!$A$1:$B$33,2,0) -> MÉXICO | D8: XONACATLÁN | E8: SALVADOR ROSAS SAAVEDRA | G8: PFC.3 MANTENIMIENTO DE PLANTACIONES FORESTALES COMERCIALES 2025 | I8: 1 | M8: 2025 | N8: PLANTACIONES FORESTALES COMERCIALES
A9: PFCMAP5825160009 | B9: 16 | C9: =+VLOOKUP(B9,EDOS!$A$1:$B$33,2,0) -> MICHOACÁN DE OCAMPO | D9: CHERÁN | E9: J. ROSALIO MACIAS GUARDIAN | G9: PFC.3 MANTENIMIENTO DE PLANTACIONES FORESTALES COMERCIALES 2025 | I9: 49.65 | M9: 2025 | N9: PLANTACIONES FORESTALES COMERCIALES
A10: PFCMAP5825160022 | B10: 16 | C10: =+VLOOKUP(B10,EDOS!$A$1:$B$33,2,0) -> MICHOACÁN DE OCAMPO | D10: CHERÁN | E10: JOSEFINA ESTRADA VELAZQUEZ | G10: PFC.3 MANTENIMIENTO DE PLANTACIONES FORESTALES COMERCIALES 2025 | I10: 27.85 | M10: 2025 | N10: PLANTACIONES FORESTALES COMERCIALES
A11: PFCMAP5825160030 | B11: 16 | C11: =+VLOOKUP(B11,EDOS!$A$1:$B$33,2,0) -> MICHOACÁN DE OCAMPO | D11: ZINAPÉCUARO | E11: EJIDO UCAREO | G11: PFC.3 MANTENIMIENTO DE PLANTACIONES FORESTALES COMERCIALES 2025 | I11: 35.33 | M11: 2025 | N11: PLANTACIONES FORESTALES COMERCIALES
A12: PFCMAP5825160024 | B12: 16 | C12: =+VLOOKUP(B12,EDOS!$A$1:$B$33,2,0) -> MICHOACÁN DE OCAMPO | D12: CHERÁN | E12: FRANCISCO NINIZ SILVA | G12: PFC.3 MANTENIMIENTO DE PLANTACIONES FORESTALES COMERCIALES 2025 | I12: 50 | M12: 2025 | N12: PLANTACIONES FORESTALES COMERCIALES
A13: PFCMAP5825160017 | B13: 16 | C13: =+VLOOKUP(B13,EDOS!$A$1:$B$33,2,0) -> MICHOACÁN DE OCAMPO | D13: IRIMBO | E13: MIRASOL SOTO CORREA | G13: PFC.3 MANTENIMIENTO DE PLANTACIONES FORESTALES COMERCIALES 2025 | I13: 13.95 | M13: 2025 | N13: PLANTACIONES FORESTALES COMERCIALES
... A15: PFCPAP5825160009 | B15: 16 | C15: =+VLOOKUP(B15,EDOS!$A$1:$B$33,2,0) -> MICHOACÁN DE OCAMPO | D15: ZACAPU | E15: EJIDO BUENA VISTA | G15: PFC.1 PLANTACIONES FORESTALES COMERCIALES 2025 | I15: 18.2 | M15: 2025 | N15: PLANTACIONES FORESTALES COMERCIALES

Sheet H_MFC
A1: FOL_PROG | B1: CVE_EDO | C1: ESTADO | D1: MUNICIPIO | E1: SOLICITANT | F1: TIPO_PROP | G1: CONCEPTO | H1: ESQUEMA | I1: SUP_HA | J1: MONTO_CNF | K1: MONTO_PI | L1: MONTO_TOT | M1: EJERCICIO | N1: GERENCIA
A2: ACOMAP5725160001 | B2: 16 | C2: MICHOACÁN DE OCAMPO | D2: QUERÉNDARO | E2: EJIDO OTZUMATLAN O RIO DE PARRAS | G2: MFC.2.7 ACOMPAÑAMIENTO A LAS AUDITORÍAS TÉCNICAS PREVENTIVAS (ATP), CERTIFICACIÓN FORESTAL NACIONAL O INTERNACIONAL O AUDITORIAS INTERMEDIAS 2025 | J2: 63283 | M2: 2025 | N2: MANEJO FORESTAL COMUNITARIO
A3: ACOMAP5725160003 | B3: 16 | C3: MICHOACÁN DE OCAMPO | D3: TLALPUJAHUA | E3: EJIDO PUERTO BERMEO | G3: MFC.2.7 ACOMPAÑAMIENTO A LAS AUDITORÍAS TÉCNICAS PREVENTIVAS (ATP), CERTIFICACIÓN FORESTAL NACIONAL O INTERNACIONAL O AUDITORIAS INTERMEDIAS 2025 | J3: 139960 | M3: 2025 | N3: MANEJO FORESTAL COMUNITARIO
A4: ACTPAP5725010002 | B4: 01 | C4: AGUASCALIENTES | D4: EL LLANO | E4: EJIDO PALO ALTO | G4: MFC.3.1 ACTUALIZACIÓN DEL PADRÓN DE EJIDATARIOS O COMUNEROS 2025 | J4: 70000 | M4: 2025 | N4: MANEJO FORESTAL COMUNITARIO
A5: ACTPAP5725100015 | B5: 10 | C5: DURANGO | D5: MEZQUITAL | E5: SAN FRANCISCO DE OCOTAN | G5: MFC.3.1 ACTUALIZACIÓN DEL PADRÓN DE EJIDATARIOS O COMUNEROS 2025 | J5: 70000 | M5: 2025 | N5: MANEJO FORESTAL COMUNITARIO
A6: APECAP4023100019 | B6: 10 | C6: DURANGO | D6: MEZQUITAL | E6: COMUNIDAD SAN ANTONIO DE PADUA | G6: MFCCV.2.2.1 ACTUALIZACIÓN DEL PADRÓN DE EJIDATARIOS O COMUNEROS | J6: 70000 | M6: 2023 | N6: MANEJO FORESTAL COMUNITARIO
A7: APECAP4624100007 | B7: 10 | C7: DURANGO | D7: MEZQUITAL | E7: COMUNIDAD SANTA MARIA DE OCOTAN Y XOCONOXTLE | G7: MFCCV.2.2.1 ACTUALIZACIÓN DEL PADRÓN DE EJIDATARIOS O COMUNEROS 2024 | J7: 70000 | M7: 2024 | N7: MANEJO FORESTAL COMUNITARIO
A8: APECAP4624100040 | B8: 10 | C8: DURANGO | D8: SÚCHIL | E8: EJIDO SAN ANTONIO DE MULEROS | G8: MFCCV.2.2.1 ACTUALIZACIÓN DEL PADRÓN DE EJIDATARIOS O COMUNEROS 2024 | J8: 70000 | M8: 2024 | N8: MANEJO FORESTAL COMUNITARIO
A9: APECAP4624100041 | B9: 10 | C9: DURANGO | D9: SÚCHIL | E9: EJIDO LOS AZULES | G9: MFCCV.2.2.1 ACTUALIZACIÓN DEL PADRÓN DE EJIDATARIOS O COMUNEROS 2024 | J9: 70000 | M9: 2024 | N9: MANEJO FORESTAL COMUNITARIO
A10: APECAP4624110002 | B10: 11 | C10: GUANAJUATO | D10: SAN MIGUEL DE ALLENDE | E10: EJIDO LA HUERTA | G10: MFCCV.2.2.1 ACTUALIZACIÓN DEL PADRÓN DE EJIDATARIOS O COMUNEROS 2024 | J10: 70000 | M10: 2024 | N10: MANEJO FORESTAL COMUNITARIO
A11: APECAP4624110009 | B11: 11 | C11: GUANAJUATO | D11: SAN MIGUEL DE ALLENDE | E11: EJIDO TIERRA BLANCA | G11: MFCCV.2.2.1 ACTUALIZACIÓN DEL PADRÓN DE EJIDATARIOS O COMUNEROS 2024 | J11: 70000 | M11: 2024 | N11: MANEJO FORESTAL COMUNITARIO
A12: APECAP4624150012 | B12: 15 | C12: MÉXICO | D12: TEMOAYA | E12: EJIDO SAN PEDRO ARRIBA | G12: MFCCV.2.2.1 ACTUALIZACIÓN DEL PADRÓN DE EJIDATARIOS O COMUNEROS 2024 | J12: 70000 | M12: 2024 | N12: MANEJO FORESTAL COMUNITARIO
A13: APECAP4624150017 | B13: 15 | C13: MÉXICO | D13: SAN JOSÉ DEL RINCÓN | E13: EJIDO SAN JUAN PALO SECO | G13: MFCCV.2.2.1 ACTUALIZACIÓN DEL PADRÓN DE EJIDATARIOS O COMUNEROS 2024 | J13: 70000 | M13: 2024 | N13: MANEJO FORESTAL COMUNITARIO
... A233: TURIAP4624220001 | B233: 22 | C233: QUERÉTARO | D233: AMEALCO DE BONFIL | E233: LAGUNA DE SERVIN | G233: MFCCV.2.1.8 TURISMO EN ÁREAS FORESTALES 2024 | J233: 229215 | M233: 2024 | N233: MANEJO FORESTAL COMUNITARIO

Sheet EDOS
A1: CVEGEO | B1: ESTADO
A2: 01 | B2: AGUASCALIENTES
A3: 02 | B3: BAJA CALIFORNIA
A4: 03 | B4: BAJA CALIFORNIA SUR
A5: 04 | B5: CAMPECHE
A6: 05 | B6: COAHUILA DE ZARAGOZA
A7: 06 | B7: COLIMA
A8: 07 | B8: CHIAPAS
A9: 08 | B9: CHIHUAHUA
A10: 09 | B10: CIUDAD DE MÉXICO
A11: 10 | B11: DURANGO
A12: 11 | B12: GUANAJUATO
... A33: 32 | B33: ZACATECAS

Sheet PFC
A1: FID | B1: Shape | C1: fid_1 | D1: FOLIO_SOLI | E1: FOLIO_APOY | F1: ASIGNACION | G1: Componente | H1: Concepto_d | I1: MUNICIPIO_ | J1: MODALIDAD_ | K1: BENEFICIAR | L1: SUPER
A2: 0 | B2: Polygon | C2: 1 | D2: S202516000537 | E2: PFCMAP5825160016 | F2: 2025 | G2: COMPONENTE II. PLANTACIONES FORESTALES COMERCIALES Y AGROFORESTALES | H2: PLANTACIONES FORESTALES COMERCIALES Y AGROFORESTALES (PFCA) | I2: IRIMBO | J2: PFC.3 MANTENIMIENTO DE PLANTACIONES FORESTALES COMERCIALES 2025 | K2: YOLANDA HERNANDEZ MARIN | L2: 1.43
A3: 1 | B3: Polygon | C3: 2 | D3: S202516000522 | E3: PFCMAP5825160014 | F3: 2025 | G3: COMPONENTE II. PLANTACIONES FORESTALES COMERCIALES Y AGROFORESTALES | H3: PLANTACIONES FORESTALES COMERCIALES Y AGROFORESTALES (PFCA) | I3: ZACAPU | J3: PFC.3 MANTENIMIENTO DE PLANTACIONES FORESTALES COMERCIALES 2025 | K3: EJIDO TIRINDARO | L3: 17.42
A4: 2 | B4: Polygon | C4: 3 | D4: S202516000475 | E4: PFCMAP5825160006 | F4: 2025 | G4: COMPONENTE II. PLANTACIONES FORESTALES COMERCIALES Y AGROFORESTALES | H4: PLANTACIONES FORESTALES COMERCIALES Y AGROFORESTALES (PFCA) | I4: TANGANCÍCUARO | J4: PFC.3 MANTENIMIENTO DE PLANTACIONES FORESTALES COMERCIALES 2025 | K4: COMUNIDAD INDIGENA DE PATAMBAN | L4: 35.88
A5: 3 | B5: Polygon | C5: 4 | D5: S202516000520 | E5: PFCMAP5825160013 | F5: 2025 | G5: COMPONENTE II. PLANTACIONES FORESTALES COMERCIALES Y AGROFORESTALES | H5: PLANTACIONES FORESTALES COMERCIALES Y AGROFORESTALES (PFCA) | I5: ZACAPU | J5: PFC.3 MANTENIMIENTO DE PLANTACIONES FORESTALES COMERCIALES 2025 | K5: EJIDO BUENA VISTA | L5: 50
A6: 4 | B6: Polygon | C6: 5 | D6: S202416000436 | E6: PFC1AP4724160007 | F6: 2024 | G6: COMPONENTE II. PLANTACIONES FORESTALES COMERCIALES Y AGROFORESTALES (PFCA) | H6: PFCA.1 PLANTACIONES FORESTALES COMERCIALES 2024 | I6: IRIMBO | J6: PFCA.1 PLANTACIONES FORESTALES COMERCIALES 2024 | K6: YOLANDA HERNANDEZ MARIN | L6: 1.9
A7: 5 | B7: Polygon | C7: 6 | D7: S202516000507 | E7: PFCMAP5825160010 | F7: 2025 | G7: COMPONENTE II. PLANTACIONES FORESTALES COMERCIALES Y AGROFORESTALES | H7: PLANTACIONES FORESTALES COMERCIALES Y AGROFORESTALES (PFCA) | I7: CHERÁN | J7: PFC.3 MANTENIMIENTO DE PLANTACIONES FORESTALES COMERCIALES 2025 | K7: JOSUE VELAZQUEZ VELAZQUEZ | L7: 50
A8: 6 | B8: Polygon | C8: 7 | D8: S202515000156 | E8: PFCMAP5825150011 | F8: 2025 | G8: COMPONENTE II. PLANTACIONES FORESTALES COMERCIALES Y AGROFORESTALES | H8: PLANTACIONES FORESTALES COMERCIALES Y AGROFORESTALES (PFCA) | I8: XONACATLÁN | J8: PFC.3 MANTENIMIENTO DE PLANTACIONES FORESTALES COMERCIALES 2025 | K8: SALVADOR ROSAS SAAVEDRA | L8: 1
A9: 7 | B9: Polygon | C9: 8 | D9: S202516000506 | E9: PFCMAP5825160009 | F9: 2025 | G9: COMPONENTE II. PLANTACIONES FORESTALES COMERCIALES Y AGROFORESTALES | H9: PLANTACIONES FORESTALES COMERCIALES Y AGROFORESTALES (PFCA) | I9: CHERÁN | J9: PFC.3 MANTENIMIENTO DE PLANTACIONES FORESTALES COMERCIALES 2025 | K9: J. ROSALIO MACIAS GUARDIAN | L9: 49.65
A10: 8 | B10: Polygon | C10: 9 | D10: S202516000552 | E10: PFCMAP5825160022 | F10: 2025 | G10: COMPONENTE II. PLANTACIONES FORESTALES COMERCIALES Y AGROFORESTALES | H10: PLANTACIONES FORESTALES COMERCIALES Y AGROFORESTALES (PFCA) | I10: CHERÁN | J10: PFC.3 MANTENIMIENTO DE PLANTACIONES FORESTALES COMERCIALES 2025 | K10: JOSEFINA ESTRADA VELAZQUEZ | L10: 27.85
A11: 9 | B11: Polygon | C11: 10 | D11: S202516000620 | E11: PFCMAP5825160030 | F11: 2025 | G11: COMPONENTE II. PLANTACIONES FORESTALES COMERCIALES Y AGROFORESTALES | H11: PLANTACIONES FORESTALES COMERCIALES Y AGROFORESTALES (PFCA) | I11: ZINAPÉCUARO | J11: PFC.3 MANTENIMIENTO DE PLANTACIONES FORESTALES COMERCIALES 2025 | K11: EJIDO UCAREO | L11: 35.33
A12: 10 | B12: Polygon | C12: 11 | D12: S202516000554 | E12: PFCMAP5825160024 | F12: 2025 | G12: COMPONENTE II. PLANTACIONES FORESTALES COMERCIALES Y AGROFORESTALES | H12: PLANTACIONES FORESTALES COMERCIALES Y AGROFORESTALES (PFCA) | I12: CHERÁN | J12: PFC.3 MANTENIMIENTO DE PLANTACIONES FORESTALES COMERCIALES 2025 | K12: FRANCISCO NINIZ SILVA | L12: 50
A13: 11 | B13: Polygon | C13: 12 | D13: S202516000542 | E13: PFCMAP5825160017 | F13: 2025 | G13: COMPONENTE II. PLANTACIONES FORESTALES COMERCIALES Y AGROFORESTALES | H13: PLANTACIONES FORESTALES COMERCIALES Y AGROFORESTALES (PFCA) | I13: IRIMBO | J13: PFC.3 MANTENIMIENTO DE PLANTACIONES FORESTALES COMERCIALES 2025 | K13: MIRASOL SOTO CORREA | L13: 13.95
... A15: 13 | B15: Polygon | C15: 14 | D15: S202516000520 | E15: PFCPAP5825160009 | F15: 2025 | G15: COMPONENTE II. PLANTACIONES FORESTALES COMERCIALES Y AGROFORESTALES | H15: PLANTACIONES FORESTALES COMERCIALES Y AGROFORESTALES (PFCA) | I15: ZACAPU | J15: PFC.1 PLANTACIONES FORESTALES COMERCIALES 2025 | K15: EJIDO BUENA VISTA | L15: 18.2
B18: Homologada | C18: PSA | D18: PFC | E18: MFC
B19: FOL_PROG | C19: FOL_PROG | D19: FOLIO_APOY | E19: Folioapoyo
B20: CVE_EDO | C20: CVE_EDO
B21: ESTADO | C21: ESTADO | E21: ESTADO
B22: MUNICIPIO | C22: MUNICIPIO | D22: MUNICIPIO_ | E22: Municipio
B23: SOLICITANT | C23: SOLICITANT | D23: BENEFICIAR | E23: Persona_be
B24: TIPO_PROP | C24: TIPO_PROP
B25: CONCEPTO | C25: CONCEPTO | D25: MODALIDAD_ | E25: b
B26: ESQUEMA | C26: ESQUEMA | D26: Concepto_d
B27: SUP_HA | C27: SUP_HA | D27: SUPER
B28: MONTO_CNF | C28: MONTO_CNF | E28: Monto_asig
B29: MONTO_PI | C29: MONTO_PI
B30: MONTO_TOT | C30: MONTO_TOT
B31: EJERCICIO | C31: EJERCICIO | D31: ASIGNACION | E31: Año_de_as
B32: GERENCIA

Sheet Hoja1
B1: Ejercicio Cuenca Lerma-Santiago
B2: Información geográfica
B4: DATOS HOMOLOGADOS | C4: PSA | D4: PFC | E4: MFC
B5: FOL_PROG | C5: FOL_PROG | D5: FOLIO_APOY | E5: Folioapoyo
B6: CVE_EDO | C6: CVE_EDO
B7: ESTADO | C7: ESTADO | E7: ESTADO
B8: MUNICIPIO | C8: MUNICIPIO | D8: MUNICIPIO_ | E8: Municipio
B9: SOLICITANT | C9: SOLICITANT | D9: BENEFICIAR | E9: Persona_be
B10: TIPO_PROP | C10: TIPO_PROP
B11: CONCEPTO | C11: CONCEPTO | D11: MODALIDAD_ | E11: b
B12: ESQUEMA | C12: ESQUEMA | D12: Concepto_d
B13: SUP_HA | C13: SUP_HA | D13: SUPER
B14: MONTO_CNF | C14: MONTO_CNF | E14: Monto_asig
B15: MONTO_PI | C15: MONTO_PI
B16: MONTO_TOT | C16: MONTO_TOT
B17: EJERCICIO | C17: EJERCICIO | D17: ASIGNACION | E17: Año_de_as
B18: GERENCIA

Sheet Hoja3

Sheet MFC
A1: FID | B1: Shape * | C1: Folioapoyo | D1: No | E1: ESTADO | F1: Municipio | G1: Componente | H1: b | I1: Folio_de_s | J1: Folio_de_a | K1: Persona_be | L1: Monto_asig | M1: Monto_paga | N1: Monto_por | O1: Año_de_as | P1: Gerencia
A2: 0 | B2: Polygon | C2: ACOMAP5725160001 | D2: 185 | E2: MICHOACÁN | F2: QUERÉNDARO | G2: I | H2: MFC.2.7 ACOMPAÑAMIENTO A LAS AUDITORÍAS TÉCNICAS PREVENTIVAS (ATP), CERTIFICACIÓN FORESTAL NACIONAL O INTERNACIONAL O AUDITORIAS INTERMEDIAS 2025 | I2: S202516000340 | J2: ACOMAP5725160001 | K2: EJIDO OTZUMATLAN O RIO DE PARRAS | L2: 63283 | M2: 50626.4 | N2: 12656.6 | O2: 2025 | P2: GMFC
A3: 1 | B3: Polygon | C3: ACOMAP5725160003 | D3: 186 | E3: MICHOACÁN | F3: TLALPUJAHUA | G3: I | H3: MFC.2.7 ACOMPAÑAMIENTO A LAS AUDITORÍAS TÉCNICAS PREVENTIVAS (ATP), CERTIFICACIÓN FORESTAL NACIONAL O INTERNACIONAL O AUDITORIAS INTERMEDIAS 2025 | I3: S202516000588 | J3: ACOMAP5725160003 | K3: EJIDO PUERTO BERMEO | L3: 139960 | M3: 111968 | N3: 27992 | O3: 2025 | P3: GMFC
A4: 2 | B4: Polygon | C4: ACTPAP5725010002 | D4: 125 | E4: AGUASCALIENTES | F4: EL LLANO | G4: I | H4: MFC.3.1 ACTUALIZACIÓN DEL PADRÓN DE EJIDATARIOS O COMUNEROS 2025 | I4: S202501000020 | J4: ACTPAP5725010002 | K4: EJIDO PALO ALTO | L4: 70000 | M4: 56000 | N4: 14000 | O4: 2025 | P4: GMFC
A5: 3 | B5: Polygon | C5: ACTPAP5725100015 | D5: 131 | E5: DURANGO | F5: MEZQUITAL | G5: I | H5: MFC.3.1 ACTUALIZACIÓN DEL PADRÓN DE EJIDATARIOS O COMUNEROS 2025 | I5: S202510000239 | J5: ACTPAP5725100015 | K5: SAN FRANCISCO DE OCOTAN | L5: 70000 | M5: 56000 | N5: 14000 | O5: 2025 | P5: GMFC
A6: 4 | B6: Polygon | C6: APECAP4023100019 | D6: 35 | E6: DURANGO | F6: MEZQUITAL | G6: I | H6: MFCCV.2.2.1 ACTUALIZACIÓN DEL PADRÓN DE EJIDATARIOS O COMUNEROS | I6: S202310000245 | J6: APECAP4023100019 | K6: COMUNIDAD SAN ANTONIO DE PADUA | L6: 70000 | M6: 56000 | N6: 14000 | O6: 2023 | P6: GMFC
A7: 5 | B7: Polygon | C7: APECAP4624100007 | D7: 49 | E7: DURANGO | F7: MEZQUITAL | G7: I | H7: MFCCV.2.2.1 ACTUALIZACIÓN DEL PADRÓN DE EJIDATARIOS O COMUNEROS 2024 | I7: S202410000168 | J7: APECAP4624100007 | K7: COMUNIDAD SANTA MARIA DE OCOTAN Y XOCONOXTLE | L7: 70000 | M7: 56000 | N7: 14000 | O7: 2024 | P7: GMFC
A8: 6 | B8: Polygon | C8: APECAP4624100040 | D8: 120 | E8: DURANGO | F8: SÚCHIL | G8: I | H8: MFCCV.2.2.1 ACTUALIZACIÓN DEL PADRÓN DE EJIDATARIOS O COMUNEROS 2024 | I8: S202410000403 | J8: APECAP4624100040 | K8: EJIDO SAN ANTONIO DE MULEROS | L8: 70000 | M8: 56000 | N8: 14000 | O8: 2024 | P8: GMFC
A9: 7 | B9: Polygon | C9: APECAP4624100041 | D9: 54 | E9: DURANGO | F9: SÚCHIL | G9: I | H9: MFCCV.2.2.1 ACTUALIZACIÓN DEL PADRÓN DE EJIDATARIOS O COMUNEROS 2024 | I9: S202410000408 | J9: APECAP4624100041 | K9: EJIDO LOS AZULES | L9: 70000 | M9: 56000 | N9: 14000 | O9: 2024 | P9: GMFC
A10: 8 | B10: Polygon | C10: APECAP4624110002 | D10: 58 | E10: GUANAJUATO | F10: SAN MIGUEL DE ALLENDE | G10: I | H10: MFCCV.2.2.1 ACTUALIZACIÓN DEL PADRÓN DE EJIDATARIOS O COMUNEROS 2024 | I10: S202411000017 | J10: APECAP4624110002 | K10: EJIDO LA HUERTA | L10: 70000 | M10: 56000 | N10: 14000 | O10: 2024 | P10: GMFC
A11: 9 | B11: Polygon | C11: APECAP4624110009 | D11: 62 | E11: GUANAJUATO | F11: SAN MIGUEL DE ALLENDE | G11: I | H11: MFCCV.2.2.1 ACTUALIZACIÓN DEL PADRÓN DE EJIDATARIOS O COMUNEROS 2024 | I11: S202411000054 | J11: APECAP4624110009 | K11: EJIDO TIERRA BLANCA | L11: 70000 | M11: 56000 | N11: 14000 | O11: 2024 | P11: GMFC
A12: 10 | B12: Polygon | C12: APECAP4624150012 | D12: 93 | E12: MÉXICO | F12: TEMOAYA | G12: I | H12: MFCCV.2.2.1 ACTUALIZACIÓN DEL PADRÓN DE EJIDATARIOS O COMUNEROS 2024 | I12: S202415000173 | J12: APECAP4624150012 | K12: EJIDO SAN PEDRO ARRIBA | L12: 70000 | M12: 56000 | N12: 14000 | O12: 2024 | P12: GMFC
A13: 11 | B13: Polygon | C13: APECAP4624150017 | D13: 88 | E13: MÉXICO | F13: SAN JOSÉ DEL RINCÓN | G13: I | H13: MFCCV.2.2.1 ACTUALIZACIÓN DEL PADRÓN DE EJIDATARIOS O COMUNEROS 2024 | I13: S202415000209 | J13: APECAP4624150017 | K13: EJIDO SAN JUAN PALO SECO | L13: 70000 | M13: 56000 | N13: 14000 | O13: 2024 | P13: GMFC
... A233: 231 | B233: Polygon | C233: TURIAP4624220001 | D233: 110 | E233: QUERÉTARO | F233: AMEALCO DE BONFIL | G233: I | H233: MFCCV.2.1.8 TURISMO EN ÁREAS FORESTALES 2024 | I233: S202422000040 | J233: TURIAP4624220001 | K233: LAGUNA DE SERVIN | L233: 229215 | M233: 183372 | N233: 45843 | O233: 2024 | P233: GMFC
